dogstatsd.py
setup.py
dogstatsd_python_fixed.egg-info/PKG-INFO
dogstatsd_python_fixed.egg-info/SOURCES.txt
dogstatsd_python_fixed.egg-info/dependency_links.txt
dogstatsd_python_fixed.egg-info/top_level.txt