Metadata-Version: 1.0
Name: dogstatsd-python-fixed
Version: 0.5.0
Summary: Python bindings to Datadog's API and a user-facing command line tool.
Home-page: http://www.datadoghq.com
Author: Datadog, Inc. (packages@datadoghq.com), Steve Leonard
Author-email: sleonard76@gmail.com
License: BSD
Keywords: datadog data statsd dogstatsd metrics
Platform: UNKNOWN
